{
    "name": "postgres-connector",
    "config": {
        "connector.class": "io.debezium.connector.postgresql.PostgresConnector",
        "tasks.max": "1",
        "database.hostname": "postgres",
        "database.port": "5432",
        "database.user": "airflow",
        "database.password": "airflow",
        "database.dbname": "airflow",
        "database.server.name": "dbserver1",
        "schema.include.list": "public",
        "table.include.list": "public.users",
        "plugin.name": "pgoutput"
    }
}